tcw_tasks/__init__.py
tcw_tasks/models.py
tcw_tasks/notify.py
tcw_tasks/templates.py
tcw_tasks/utils.py
tcw_tasks-0.6.0.dist-info/LICENSE
tcw_tasks-0.6.0.dist-info/METADATA
tcw_tasks-0.6.0.dist-info/WHEEL
tcw_tasks-0.6.0.dist-info/entry_points.txt
tcw_tasks-0.6.0.dist-info/top_level.txt
tcw_tasks-0.6.0.dist-info/RECORD
