Metadata-Version: 2.1
Name: tcw-tasks
Version: 0.6.0
Summary: contest cleanup script for tcw app
Author: J Leary
Author-email: tinycontestwinners@gmail.com
License-File: LICENSE
Requires-Dist: tcw >=0.1.13
Requires-Dist: jinja2
Requires-Dist: sendgrid
